memory_tempfile/__init__.py
memory_tempfile/memory_tempfile.py
memory_tempfile-2.2.2.dist-info/LICENSE
memory_tempfile-2.2.2.dist-info/WHEEL
memory_tempfile-2.2.2.dist-info/METADATA
memory_tempfile-2.2.2.dist-info/RECORD
