Metadata-Version: 2.1
Name: memory-tempfile
Version: 2.2.2
Summary: Helper functions to identify and use paths on the OS (Linux-only for now) where RAM-based tempfiles can be created.
Home-page: https://github.com/mbello/memory-tempfile
License: CC0-1.0
Keywords: tempfile in RAM,tempfile in memory,file in memory,tempfs,ramdisk,/dev/shm,/run/user
Author: mbello
Author-email: mbello@users.noreply.github.com
Requires-Python: >=3.6,<4.0
Classifier: License :: CC0 1.0 Universal (CC0 1.0) Public Domain Dedication
Classifier: Programming Language :: Python :: 3
Classifier: Programming Language :: Python :: 3.6
Classifier: Programming Language :: Python :: 3.7
Classifier: Programming Language :: Python :: 3.8
Project-URL: Repository, https://github.com/mbello/memory-tempfile
